{
    "agenix": {
        "branch": "main",
        "description": "age-encrypted secrets for NixOS",
        "homepage": "https://matrix.to/#/#agenix:nixos.org",
        "owner": "ryantm",
        "repo": "agenix",
        "rev": "e600439ec4c273cf11e06fe4d9d906fb98fa097c",
        "sha256": "006ngydiykjgqs85cl19h9klq8kaqm5zs0ng51dnwy7nzgqxzsdr",
        "type": "tarball",
        "url": "https://github.com/ryantm/agenix/archive/e600439ec4c273cf11e06fe4d9d906fb98fa097c.tar.gz",
        "url_template": "https://github.com/<owner>/<repo>/archive/<rev>.tar.gz"
    },
    "nixpkgs": {
        "branch": "nixos-24.11",
        "description": "Nix Packages collection",
        "homepage": "",
        "owner": "NixOS",
        "repo": "nixpkgs",
        "rev": "a880f49904d68b5e53338d1e8c7bf80f59903928",
        "sha256": "0gs1hkm6piwknanfa3qncm2i2g81blqx2rxp5d629396wla670d3",
        "type": "tarball",
        "url": "https://github.com/NixOS/nixpkgs/archive/a880f49904d68b5e53338d1e8c7bf80f59903928.tar.gz",
        "url_template": "https://github.com/<owner>/<repo>/archive/<rev>.tar.gz"
    },
    "unstable": {
        "branch": "nixos-unstable",
        "description": "Nix Packages collection & NixOS",
        "homepage": "",
        "owner": "NixOS",
        "repo": "nixpkgs",
        "rev": "063dece00c5a77e4a0ea24e5e5a5bd75232806f8",
        "sha256": "0hfwkq9524r2zvblizrywbh5895nr7v2b1vy8ciys5rlfjvkajlw",
        "type": "tarball",
        "url": "https://github.com/NixOS/nixpkgs/archive/063dece00c5a77e4a0ea24e5e5a5bd75232806f8.tar.gz",
        "url_template": "https://github.com/<owner>/<repo>/archive/<rev>.tar.gz"
    }
}
