{
    "agenix": {
        "branch": "main",
        "description": "age-encrypted secrets for NixOS",
        "homepage": "https://matrix.to/#/#agenix:nixos.org",
        "owner": "ryantm",
        "repo": "agenix",
        "rev": "13ac9ac6d68b9a0896e3d43a082947233189e247",
        "sha256": "196k2gchfy4y0258j6n15zd96harinzx91yqcmfrv1dvgwk9x94c",
        "type": "tarball",
        "url": "https://github.com/ryantm/agenix/archive/13ac9ac6d68b9a0896e3d43a082947233189e247.tar.gz",
        "url_template": "https://github.com/<owner>/<repo>/archive/<rev>.tar.gz"
    },
    "nixpkgs": {
        "branch": "nixos-23.11",
        "description": "Nix Packages collection",
        "homepage": "",
        "owner": "NixOS",
        "repo": "nixpkgs",
        "rev": "b4372c4924d9182034066c823df76d6eaf1f4ec4",
        "sha256": "03daj0laqlqdp053wr2fznwjfbkkyh12qq1wa87zdsgdnnrgd6sc",
        "type": "tarball",
        "url": "https://github.com/NixOS/nixpkgs/archive/b4372c4924d9182034066c823df76d6eaf1f4ec4.tar.gz",
        "url_template": "https://github.com/<owner>/<repo>/archive/<rev>.tar.gz"
    },
    "unstable": {
        "branch": "nixos-unstable-small",
        "description": "Nix Packages collection",
        "homepage": "",
        "owner": "nixos",
        "repo": "nixpkgs",
        "rev": "1f8d62a69936dd899d0e7c955537b2f4ca5bc623",
        "sha256": "1s812yizixfalbp9p67sbkhb6dccshbpi5iyhc47jhl21iymkmw3",
        "type": "tarball",
        "url": "https://github.com/nixos/nixpkgs/archive/1f8d62a69936dd899d0e7c955537b2f4ca5bc623.tar.gz",
        "url_template": "https://github.com/<owner>/<repo>/archive/<rev>.tar.gz"
    }
}
