{
    "agenix": {
        "branch": "main",
        "description": "age-encrypted secrets for NixOS",
        "homepage": "https://matrix.to/#/#agenix:nixos.org",
        "owner": "ryantm",
        "repo": "agenix",
        "rev": "d8c973fd228949736dedf61b7f8cc1ece3236792",
        "sha256": "01id7i7gw3r56b2p95411sbmbmmsarpzamig4h8rxbi4bljvnxzm",
        "type": "tarball",
        "url": "https://github.com/ryantm/agenix/archive/d8c973fd228949736dedf61b7f8cc1ece3236792.tar.gz",
        "url_template": "https://github.com/<owner>/<repo>/archive/<rev>.tar.gz"
    },
    "nixpkgs": {
        "branch": "nixos-23.05",
        "description": "Nix Packages collection",
        "homepage": "",
        "owner": "NixOS",
        "repo": "nixpkgs",
        "rev": "ae521bd4e460b076a455dca8b13f4151489a725c",
        "sha256": "0d7430713rk04ps5xr77ic225lfgrdp7f1ii1s4dm6zaygmvnhjd",
        "type": "tarball",
        "url": "https://github.com/NixOS/nixpkgs/archive/ae521bd4e460b076a455dca8b13f4151489a725c.tar.gz",
        "url_template": "https://github.com/<owner>/<repo>/archive/<rev>.tar.gz"
    },
    "unstable": {
        "branch": "nixos-unstable-small",
        "description": "Nix Packages collection",
        "homepage": "",
        "owner": "nixos",
        "repo": "nixpkgs",
        "rev": "2f4e3f6fa553264d3b8bcf4d3561c0134b625afa",
        "sha256": "08hrdkh365diyvhcdb1dxj1kc79kyrsz27jrg08h63vpa3l4aprp",
        "type": "tarball",
        "url": "https://github.com/nixos/nixpkgs/archive/2f4e3f6fa553264d3b8bcf4d3561c0134b625afa.tar.gz",
        "url_template": "https://github.com/<owner>/<repo>/archive/<rev>.tar.gz"
    }
}
